appserver_sdk_python_ai/__init__.py
appserver_sdk_python_ai/llm/__init__.py
appserver_sdk_python_ai/llm/core/enums/__init__.py
appserver_sdk_python_ai/llm/core/enums/huggingface_model_enum.py
appserver_sdk_python_ai/llm/core/enums/openai_model_enum.py
appserver_sdk_python_ai/llm/core/enums/tokenizer_type_enum.py
appserver_sdk_python_ai/llm/core/model_manager.py
appserver_sdk_python_ai/llm/service/token_service.py
appserver_sdk_python_ai/py.typed
appserver_sdk_python_ai-0.1.0.dist-info/LICENSE
appserver_sdk_python_ai-0.1.0.dist-info/METADATA
appserver_sdk_python_ai-0.1.0.dist-info/WHEEL
appserver_sdk_python_ai-0.1.0.dist-info/RECORD
