Metadata-Version: 2.3
Name: appserver-sdk-python-ai
Version: 0.1.0
Summary: SDK Python para serviços de IA da AppServer com suporte a contagem de tokens
License: MIT
Keywords: ai,tokens,llm,openai,huggingface,sdk,tokenizer
Author: AppServer Team
Author-email: suporte@appserver.com.br
Maintainer: AppServer Team
Maintainer-email: suporte@appserver.com.br
Requires-Python: >=3.11
Classifier: Development Status :: 3 - Alpha
Classifier: Intended Audience :: Developers
Classifier: License :: OSI Approved :: MIT License
Classifier: Operating System :: OS Independent
Classifier: Programming Language :: Python :: 3
Classifier: Programming Language :: Python :: 3.11
Classifier: Programming Language :: Python :: 3.12
Classifier: Topic :: Software Development :: Libraries :: Python Modules
Classifier: Topic :: Scientific/Engineering :: Artificial Intelligence
Classifier: Topic :: Text Processing :: Linguistic
Classifier: Typing :: Typed
Provides-Extra: dev
Provides-Extra: docs
Provides-Extra: full
Provides-Extra: huggingface
Provides-Extra: openai
Provides-Extra: test
Requires-Dist: mypy (>=1.8.0) ; extra == "dev"
Requires-Dist: myst-parser (>=2.0.0) ; extra == "docs"
Requires-Dist: pre-commit (>=3.6.0) ; extra == "dev"
Requires-Dist: pytest (>=8.0.0) ; extra == "dev"
Requires-Dist: pytest (>=8.0.0) ; extra == "test"
Requires-Dist: pytest-asyncio (>=0.23.0) ; extra == "dev"
Requires-Dist: pytest-asyncio (>=0.23.0) ; extra == "test"
Requires-Dist: pytest-cov (>=4.0.0) ; extra == "dev"
Requires-Dist: pytest-cov (>=4.0.0) ; extra == "test"
Requires-Dist: ruff (>=0.12.7) ; extra == "dev"
Requires-Dist: sphinx (>=7.0.0) ; extra == "docs"
Requires-Dist: sphinx-rtd-theme (>=2.0.0) ; extra == "docs"
Requires-Dist: tiktoken (>=0.5.0,<1.0.0) ; extra == "full"
Requires-Dist: tiktoken (>=0.5.0,<1.0.0) ; extra == "openai"
Requires-Dist: torch (>=2.0.0,<3.0.0) ; extra == "full"
Requires-Dist: torch (>=2.0.0,<3.0.0) ; extra == "huggingface"
Requires-Dist: transformers (>=4.30.0,<5.0.0) ; extra == "full"
Requires-Dist: transformers (>=4.30.0,<5.0.0) ; extra == "huggingface"
Requires-Dist: types-requests (>=2.31.0) ; extra == "dev"
Project-URL: Documentation, https://appserver.com.br/docs
Project-URL: Homepage, https://appserver.com.br
